{
  "schema_version": "2.0",
  "location_id": "us-tx-austin-msa",
  "leads": [
    {
      "external_id": "df0cf8e90e10d745",
      "source": "web-search",
      "organization": "Taylor ISD",
      "organization_id": "taylor-isd-tx",
      "state": "TX",
      "county": "Williamson",
      "summary": "Taylor ISD's $147M November 2025 bond (Prop A, passed 59.61%) itemizes an artificial turf line item for baseball, softball, and other district athletic sites under 1,000-seat capacity; no per-project dollar amount or installation timeline is broken out.",
      "evidence_quote": "Surface Improvements - Artificial Turf - Baseball, Softball & Other Sites with less than 1,000 seat capacity",
      "source_url": "https://www.taylorisdvote.org/prop-a",
      "discovered_at": "2026-07-16T09:15:00Z",
      "location_id": "us-tx-austin-msa",
      "evidence": {
        "project_name": "Taylor ISD Prop A - Baseball/Softball Turf",
        "project_address": "",
        "projected_start_date": "",
        "details": "Taylor ISD's $147 million Proposition A bond, approved by voters in November 2025 (59.61% in favor), includes a bond-document line item titled 'Surface Improvements - Artificial Turf - Baseball, Softball & Other Sites with less than 1,000 seat capacity,' stated purpose 'to address usability and durability.' District-wide, multi-site item covering baseball and softball fields plus unspecified other sites below 1,000-seat capacity. No individual dollar allocation, specific site list, or construction/start timeline given.",
        "contact": {
          "first_name": "",
          "last_name": "",
          "title": "",
          "phone": "",
          "email": ""
        },
        "source_ids": [
          "SRC-012"
        ],
        "source_urls": [
          "https://www.taylorisdvote.org/prop-a"
        ],
        "matched_terms": [
          "artificial turf",
          "bond",
          "baseball/softball complex"
        ],
        "confidence": 0.8,
        "needs_review": false,
        "run_timestamp": "20260716T091500Z"
      }
    },
    {
      "external_id": "13c49fbe8583d475",
      "source": "web-search",
      "organization": "Williamson County",
      "organization_id": "williamson-county-tx",
      "state": "TX",
      "county": "Williamson",
      "summary": "Williamson County Commissioners Court approved a sponsorship agreement with Lonestar Soccer Club to convert four grass fields to FIFA-certified synthetic turf at Southwest Williamson County Regional Park in Leander; total project cost ~$8.9M, approved Jan 14, 2026.",
      "evidence_quote": "The conversion from grass to FIFA-certified synthetic turf will reduce the cost of maintenance for the fields, improve field quality and significantly increase available hours for use.",
      "source_url": "https://www.wilcotx.gov/CivicAlerts.aspx?AID=735",
      "discovered_at": "2026-07-16T09:15:00Z",
      "location_id": "us-tx-austin-msa",
      "evidence": {
        "project_name": "Southwest Williamson County Regional Park - Synthetic Turf Conversion",
        "project_address": "3005 CR-175, Leander, TX 78641",
        "projected_start_date": "",
        "details": "Press release dated January 14, 2026: Williamson County Commissioners Court approved a sponsorship agreement with Lonestar Soccer Club to convert four existing grass fields to FIFA-certified synthetic turf at Southwest Williamson County Regional Park. Supports more than 12,000 annual activities. Williamson County funds one field replacement through its Capital Improvement Program; Lonestar Soccer Club invests $6.5M for remaining three fields. Total estimated cost $8,925,020. Agreement term 8-20 years. No construction start date or bid/RFP details given.",
        "contact": {
          "first_name": "T.W.",
          "last_name": "Dieckmann",
          "title": "Parks Director, Williamson County",
          "phone": "",
          "email": ""
        },
        "source_ids": [
          "SRC-005"
        ],
        "source_urls": [
          "https://www.wilcotx.gov/CivicAlerts.aspx?AID=735"
        ],
        "matched_terms": [
          "synthetic turf",
          "soccer field",
          "capital improvement program"
        ],
        "confidence": 0.9,
        "needs_review": false,
        "run_timestamp": "20260716T091500Z"
      }
    },
    {
      "external_id": "685a8842407778a0",
      "source": "web-search",
      "organization": "Lake Travis ISD",
      "organization_id": "lake-travis-isd-tx",
      "state": "TX",
      "county": "Travis",
      "summary": "New 150-acre, $219M Highland Lakes High School (HS2) campus opening Aug. 2029 will include a football stadium, baseball field, softball field, and a combined track & field/soccer stadium; CMAR selected March 2025, $46.36M Phase 1 GMP approved Sept. 2025, site work began Jan. 26, 2026, building construction starts May 11, 2026.",
      "evidence_quote": "Football Stadium, Baseball Field, Softball Field, Track & Field/Soccer Stadium",
      "source_url": "https://www.ltisdschools.org/bond/hs2",
      "discovered_at": "2026-07-16T09:15:00Z",
      "location_id": "us-tx-austin-msa",
      "evidence": {
        "project_name": "Highland Lakes High School - New Stadium & Ballfields",
        "project_address": "Reimers-Peacock Road off SH 71, Austin, TX 78738",
        "projected_start_date": "Site work 2026-01-26; building construction 2026-05-11",
        "details": "New 150-acre, $219M second high school campus (HS2). Football Stadium, Baseball Field, Softball Field, Track & Field/Soccer Stadium, plus competition gym, practice fields, 8 tennis courts. American Constructors selected CMAR March 2025; $46.36M Phase 1 GMP approved Sept 2025. Site work 2026-01-26 to 2029-03-13; building construction 2026-05-11 to 2029-02-20; opening Aug 2029. Page does not specify turf type/synthetic surfacing for any facility -- surface material not yet confirmed.",
        "contact": {
          "first_name": "",
          "last_name": "",
          "title": "",
          "phone": "",
          "email": ""
        },
        "source_ids": [
          "SRC-009"
        ],
        "source_urls": [
          "https://www.ltisdschools.org/bond/hs2"
        ],
        "matched_terms": [
          "football stadium",
          "baseball field",
          "softball field",
          "bond",
          "CMAR",
          "Track & Field/Soccer Stadium"
        ],
        "confidence": 0.65,
        "needs_review": true,
        "run_timestamp": "20260716T091500Z"
      }
    },
    {
      "external_id": "1b12d536065a8cdb",
      "source": "web-search",
      "organization": "Austin ISD",
      "organization_id": "austin-isd-tx",
      "state": "TX",
      "county": "Travis",
      "summary": "Austin ISD's 2022 bond funds a ~$25M renovation of Nelson Field, converting the baseball field to artificial turf plus grandstand, field house, press box, restroom and concession upgrades; design began fall 2023.",
      "evidence_quote": "The project will also upgrade the baseball field to artificial turf and add new seating and lighting.",
      "source_url": "https://bond.austinschools.org/bond-projects/central-athletic-facilities",
      "discovered_at": "2026-07-16T09:15:00Z",
      "location_id": "us-tx-austin-msa",
      "evidence": {
        "project_name": "Nelson Field - Baseball Turf Renovation",
        "project_address": "7104 Berkman Drive, Austin, TX 78752",
        "projected_start_date": "Design phase began fall 2023",
        "details": "Part of Austin ISD's 2022 Bond Program (Central Athletic Facilities). Budget $25,000,000. Scope: grandstand renovations, field house updates, press box enhancements, restroom improvements, concession upgrades, converting baseball field to artificial turf with new seating and lighting. Project team: Vanir STV (PM); Stantec/Cadence McShane (Architecture & Construction). Design began fall 2023; construction timeline not specified.",
        "contact": {
          "first_name": "",
          "last_name": "",
          "title": "",
          "phone": "",
          "email": ""
        },
        "source_ids": [
          "SRC-011"
        ],
        "source_urls": [
          "https://bond.austinschools.org/bond-projects/central-athletic-facilities"
        ],
        "matched_terms": [
          "artificial turf",
          "baseball field",
          "baseball turf",
          "bond"
        ],
        "confidence": 0.9,
        "needs_review": false,
        "run_timestamp": "20260716T091500Z"
      }
    },
    {
      "external_id": "3b3cc8635aa67832",
      "source": "web-search",
      "organization": "Austin ISD",
      "organization_id": "austin-isd-tx",
      "state": "TX",
      "county": "Travis",
      "summary": "Austin ISD's 2022 bond funds a ~$6.99M renovation of Yellow Jacket Stadium (football/soccer), installing artificial turf plus a new press box, fieldhouse, scoreboard, track resurfacing, lighting, seating and concessions; design began fall 2023.",
      "evidence_quote": "Upgrades include artificial turf, press box, fieldhouse, scoreboard, resurfacing the track, lights, seating, and concessions.",
      "source_url": "https://bond.austinschools.org/bond-projects/central-athletic-facilities",
      "discovered_at": "2026-07-16T09:15:00Z",
      "location_id": "us-tx-austin-msa",
      "evidence": {
        "project_name": "Yellow Jacket Stadium - Football/Soccer Turf",
        "project_address": "3101 Hargrave Street, Austin, TX 78702",
        "projected_start_date": "Design phase began fall 2023",
        "details": "Part of Austin ISD's 2022 Bond Program (Central Athletic Facilities). Budget $6,987,758. Serves football and soccer. Scope: artificial turf installation, press box, fieldhouse renovation, scoreboard upgrade, track resurfacing, lighting, seating, concessions upgrades. Project team: Vanir STV (PM); Fuse Architecture Studio (A&E). Design began fall 2023.",
        "contact": {
          "first_name": "",
          "last_name": "",
          "title": "",
          "phone": "",
          "email": ""
        },
        "source_ids": [
          "SRC-011"
        ],
        "source_urls": [
          "https://bond.austinschools.org/bond-projects/central-athletic-facilities"
        ],
        "matched_terms": [
          "artificial turf",
          "stadium turf",
          "football/soccer field",
          "bond"
        ],
        "confidence": 0.9,
        "needs_review": false,
        "run_timestamp": "20260716T091500Z"
      }
    },
    {
      "external_id": "bf4d08614f704a53",
      "source": "web-search",
      "organization": "Austin ISD",
      "organization_id": "austin-isd-tx",
      "state": "TX",
      "county": "Travis",
      "summary": "Austin ISD's 2022 bond funds a ~$4.77M upgrade of the Burger Sports Complex baseball field to artificial turf, with new lighting and seating; design began fall 2023.",
      "evidence_quote": "Upgrades include artificial turf, lights, and seating for the baseball field.",
      "source_url": "https://bond.austinschools.org/bond-projects/central-athletic-facilities",
      "discovered_at": "2026-07-16T09:15:00Z",
      "location_id": "us-tx-austin-msa",
      "evidence": {
        "project_name": "Burger Sports Complex - Baseball Turf Upgrade",
        "project_address": "3200 Jones Road, Austin, TX 78745",
        "projected_start_date": "Design phase began fall 2023",
        "details": "Part of Austin ISD's 2022 Bond Program (Central Athletic Facilities). Budget $4,767,000. Scope: converting baseball field to artificial turf, plus new lighting and seating. Design began fall 2023.",
        "contact": {
          "first_name": "",
          "last_name": "",
          "title": "",
          "phone": "",
          "email": ""
        },
        "source_ids": [
          "SRC-011"
        ],
        "source_urls": [
          "https://bond.austinschools.org/bond-projects/central-athletic-facilities"
        ],
        "matched_terms": [
          "artificial turf",
          "baseball field",
          "baseball turf",
          "bond"
        ],
        "confidence": 0.9,
        "needs_review": false,
        "run_timestamp": "20260716T091500Z"
      }
    },
    {
      "external_id": "1df90425f9acdb76",
      "source": "web-search",
      "organization": "Austin ISD",
      "organization_id": "austin-isd-tx",
      "state": "TX",
      "county": "Travis",
      "summary": "Austin ISD's 2022 bond funds a ~$2.67M upgrade of the Noack Sports Complex softball field to artificial turf, with new lighting and seating; design began fall 2023.",
      "evidence_quote": "Upgrades include artificial turf, lights and seating for the softball field.",
      "source_url": "https://bond.austinschools.org/bond-projects/central-athletic-facilities",
      "discovered_at": "2026-07-16T09:15:00Z",
      "location_id": "us-tx-austin-msa",
      "evidence": {
        "project_name": "Noack Sports Complex - Softball Turf Upgrade",
        "project_address": "5300 Crainway Dr, Austin, TX 78724",
        "projected_start_date": "Design phase began fall 2023",
        "details": "Part of Austin ISD's 2022 Bond Program (Central Athletic Facilities). Budget $2,667,000. Scope: converting softball field to artificial turf, plus new lighting and seating. Design began fall 2023.",
        "contact": {
          "first_name": "",
          "last_name": "",
          "title": "",
          "phone": "",
          "email": ""
        },
        "source_ids": [
          "SRC-011"
        ],
        "source_urls": [
          "https://bond.austinschools.org/bond-projects/central-athletic-facilities"
        ],
        "matched_terms": [
          "artificial turf",
          "softball field",
          "softball turf",
          "bond"
        ],
        "confidence": 0.9,
        "needs_review": false,
        "run_timestamp": "20260716T091500Z"
      }
    },
    {
      "external_id": "1f38a63144f6ac05",
      "source": "web-search",
      "organization": "City of Austin",
      "organization_id": "city-of-austin-tx",
      "state": "TX",
      "county": "Travis",
      "summary": "City of Austin (Parks and Recreation Dept.) IFB 8600 MAS1009, 'Athletic Fields Maintenance and Renovation,' covers baseball/softball, soccer, and multi-purpose fields at designated recreation centers citywide; bids due July 21, 2026 at 2:00 PM. Published summary does not explicitly confirm artificial/synthetic turf scope -- flagged for review.",
      "evidence_quote": "Maintenance of sports fields (baseball/softball, soccer, multi-purpose) at designated City recreation centers",
      "source_url": "https://financeonline.austintexas.gov/afo/account_services/solicitation/solicitation_details.cfm?sid=143424",
      "discovered_at": "2026-07-16T09:15:00Z",
      "location_id": "us-tx-austin-msa",
      "evidence": {
        "project_name": "Austin Rec Centers - Field Maintenance & Renovation",
        "project_address": "",
        "projected_start_date": "",
        "details": "IFB 8600 MAS1009, Athletic Fields Maintenance and Renovation, issued by Austin Parks and Recreation Department. Scope: maintenance of sports fields (baseball/softball, soccer, multi-purpose) at designated City recreation centers; specific sites in a separate Field Locations attachment not parseable during this review. Issue date June 15, 2026; pre-bid meeting June 23, 2026; response due July 21, 2026 2:00 PM. Budget not published. Listing does not explicitly mention artificial/synthetic turf -- scope may be limited to natural-grass maintenance; should be confirmed against full bid package before BDM outreach.",
        "contact": {
          "first_name": "Maggie",
          "last_name": "Stenz",
          "title": "",
          "phone": "(512) 974-3020",
          "email": "margaret.stenz@austintexas.gov"
        },
        "source_ids": [
          "SRC-010"
        ],
        "source_urls": [
          "https://financeonline.austintexas.gov/afo/account_services/solicitation/solicitation_details.cfm?sid=143424",
          "https://financeonline.austintexas.gov/afo/account_services/solicitation/solicitations.cfm"
        ],
        "matched_terms": [
          "invitation to bid",
          "bid",
          "soccer field",
          "baseball field",
          "softball field",
          "explicit multipurpose field reference"
        ],
        "confidence": 0.65,
        "needs_review": true,
        "run_timestamp": "20260716T091500Z"
      }
    },
    {
      "external_id": "745bf81ece49f2de",
      "source": "web-search",
      "organization": "Hays County",
      "organization_id": "hays-county-tx",
      "state": "TX",
      "county": "Hays",
      "summary": "Hays County's $2M Parks and Open Space Bond grant funds renovation of the North Hays Optimist (NHO) Youth Sportsplex in Kyle, a Pop Warner league complex for football, baseball, softball and cheer (ages 3-15); the source page does not state the surface type.",
      "evidence_quote": "The project received a $2M commitment from the Parks Bond to enhance recreational opportunities for youth sports programs and improve facility restoration.",
      "source_url": "https://www.haysparksbond.com/projects/nho-youth-sportsplex",
      "discovered_at": "2026-07-16T09:15:00Z",
      "location_id": "us-tx-austin-msa",
      "evidence": {
        "project_name": "NHO Youth Sportsplex - Field Renovation",
        "project_address": "2880 Goforth Rd, Kyle, TX 78640",
        "projected_start_date": "",
        "details": "North Hays Optimist (NHO), only Pop Warner League in Hays County, serves ages 3-15 with football, baseball, softball, cheer programs. Hays Parks Bond project page confirms $2M commitment from county's Parks and Open Space Bond (2020 Prop A, $75M total). Commissioners Court minutes Feb 11 2025 corroborate active/funded status: poor field conditions noted, grant awarded to NHO, dispute ongoing over field management. No turf, synthetic surface, or construction scope/timeline stated; surface type unconfirmed, should be verified directly with Hays County Parks or NHO.",
        "contact": {
          "first_name": "",
          "last_name": "",
          "title": "",
          "phone": "",
          "email": ""
        },
        "source_ids": [
          "SRC-006"
        ],
        "source_urls": [
          "https://www.haysparksbond.com/projects/nho-youth-sportsplex",
          "https://irp.cdn-website.com/ca0063d4/files/uploaded/02_11_2025.pdf"
        ],
        "matched_terms": [
          "bond"
        ],
        "confidence": 0.45,
        "needs_review": true,
        "run_timestamp": "20260716T091500Z"
      }
    },
    {
      "external_id": "df9bf885740c708a",
      "source": "web-search",
      "organization": "City of Round Rock",
      "organization_id": "city-of-round-rock-tx",
      "state": "TX",
      "county": "Williamson",
      "summary": "Round Rock's 2023 GO Bond-funded Athletic Performance Center at Old Settlers Park will add four multipurpose fields (plus an indoor gym and outdoor track); surface type is not specified on the city page, and status/timeline conflicts with later news reporting. Project is bond-funded and under design.",
      "evidence_quote": "The City will build an Athletic Performance Center that will include an indoor gym, outdoor track and four multipurpose fields.",
      "source_url": "https://www.roundrocktexas.gov/bondprojects/athletic-performance-center/",
      "discovered_at": "2026-07-16T09:15:00Z",
      "location_id": "us-tx-austin-msa",
      "evidence": {
        "project_name": "Athletic Performance Center - Four Multipurpose Fields",
        "project_address": "3300 E. Palm Valley Blvd, Round Rock, TX 78665 (Old Settlers Park)",
        "projected_start_date": "Summer 2025",
        "details": "Part of City of Round Rock's $274M 2023 GO Bond program, under Old Settlers Park Expansion umbrella. Athletic Performance Center includes indoor gym, outdoor track, four multipurpose fields, plus parking and relocated Parks & Recreation admin offices. Official page lists status 'under design,' construction planned summer 2025 to fall 2026. Jan 2026 Community Impact report states construction already began summer 2025, completion now expected spring 2027 -- city page and news report disagree on status/date. Neither source specifies whether the four multipurpose fields will be synthetic turf, natural grass, or a mix -- unconfirmed, needs direct confirmation with city contact.",
        "contact": {
          "first_name": "Katie",
          "last_name": "Baker",
          "title": "Park Development Manager",
          "phone": "",
          "email": "kbaker@roundrocktexas.gov"
        },
        "source_ids": [
          "SRC-007"
        ],
        "source_urls": [
          "https://www.roundrocktexas.gov/bondprojects/athletic-performance-center/",
          "https://www.roundrocktexas.gov/bondprojects/old-settlers-park-expansion-overall/",
          "https://communityimpact.com/austin/round-rock/government/2026/01/05/the-new-old-settlers-park-round-rock-makes-progress-on-259m-expansion/"
        ],
        "matched_terms": [
          "multipurpose field",
          "bond"
        ],
        "confidence": 0.4,
        "needs_review": true,
        "run_timestamp": "20260716T091500Z"
      }
    },
    {
      "external_id": "c0f33f9d76082745",
      "source": "web-search",
      "organization": "City of Round Rock",
      "organization_id": "city-of-round-rock-tx",
      "state": "TX",
      "county": "Williamson",
      "summary": "Round Rock is expanding the 60-acre Multipurpose Complex at Old Settlers Park with six new fields and collegiate-level press boxes; news reports describe five synthetic turf fields plus one natural grass field, ~$49M contract approved fall 2025, targeting 2027 completion under the 2023 GO Bond. City page lists status as 'under design'.",
      "evidence_quote": "This project will construct six additional fields and collegiate level press boxes to provide more space for local team practices and draw additional tournaments for sports tourism.",
      "source_url": "https://www.roundrocktexas.gov/bondprojects/multipurpose-complex-expansion/",
      "discovered_at": "2026-07-16T09:15:00Z",
      "location_id": "us-tx-austin-msa",
      "evidence": {
        "project_name": "Multipurpose Complex Expansion - Six New Fields",
        "project_address": "3300 E. Palm Valley Blvd, Round Rock, TX 78665 (Old Settlers Park)",
        "projected_start_date": "",
        "details": "Part of City of Round Rock's $274M 2023 GO Bond program, under Old Settlers Park Expansion umbrella. Existing 60-acre Multipurpose Complex opened 2017 (10 fields); ~75% local team use, 25% sports-tourism. Expansion constructs six additional fields and collegiate-level press boxes. Existing tennis complex relocating separately (excluded, not target-sport turf item). Official city page lists status 'under design' with no completion date. Independent reporting (Community Impact, SportsVenue Technology) describes five synthetic turf fields and one natural grass championship field, ~$49M construction contract approved fall 2025, completion targeted 2027, resulting 27 fields within a quarter mile. These specifics not on official city page -- should be verified directly with city before quoting to a customer.",
        "contact": {
          "first_name": "",
          "last_name": "",
          "title": "",
          "phone": "",
          "email": ""
        },
        "source_ids": [
          "SRC-007"
        ],
        "source_urls": [
          "https://www.roundrocktexas.gov/bondprojects/multipurpose-complex-expansion/",
          "https://www.roundrocktexas.gov/bondprojects/old-settlers-park-expansion-overall/",
          "https://communityimpact.com/austin/round-rock/government/2026/01/05/the-new-old-settlers-park-round-rock-makes-progress-on-259m-expansion/",
          "https://www.sportsvenue-technology.com/projects/round-rock-sports-center-expansion-takes-shape"
        ],
        "matched_terms": [
          "multipurpose field",
          "synthetic turf",
          "bond"
        ],
        "confidence": 0.65,
        "needs_review": true,
        "run_timestamp": "20260716T091500Z"
      }
    },
    {
      "external_id": "5c024f743861f427",
      "source": "web-search",
      "organization": "Leander ISD",
      "organization_id": "leander-isd-tx",
      "state": "TX",
      "county": "Williamson",
      "summary": "Leander ISD's turf replacement at A.C. Bible Jr. Memorial Stadium (football/soccer) is part of a $1.6M Bond 2023 savings reallocation shared with Monroe Stadium, approved by the Board Jan. 22, 2026; installation is reported underway as of the district's May 2026 status update (inferred from the shared project line item).",
      "evidence_quote": "The Board approved this recommendation brought forward by the Bond Oversight Committee after reviewing the condition and remaining lifespan of the existing turf, which has reached the end of its usable life and presents growing safety concerns for student-athletes.",
      "source_url": "https://www.leanderisd.org/bond_athleticsprojects/",
      "discovered_at": "2026-07-01T18:41:58Z",
      "location_id": "us-tx-austin-msa",
      "evidence": {
        "project_name": "Bible Stadium - turf replacement, football/soccer field",
        "project_address": "3301 S Bagdad Rd, Leander, TX 78641",
        "projected_start_date": "Summer 2026 (commencing later in May 2026, after Monroe Stadium, per shared bond line item)",
        "details": "Leander ISD Board (Jan. 22, 2026) approved reallocating $1.6 million in savings from the 2023 bond's high-school baseball/softball turf projects to replace end-of-life artificial turf at A.C. Bible, Jr. Memorial Stadium, alongside the same reallocation for Monroe Stadium. Bond Oversight Committee cited safety concerns from aged turf; replacement scheduled for summer 2026 to avoid disrupting the athletic season. The district's most recent page update (May 2026) confirms turf is actively being laid out at Monroe Stadium; Bible Stadium's status is inferred from the shared line item and reported to commence later in May 2026, after Monroe -- not yet independently confirmed by a Bible-specific status sentence, hence needs_review.",
        "contact": {
          "first_name": "",
          "last_name": "",
          "title": "",
          "phone": "",
          "email": ""
        },
        "source_ids": [
          "SRC-001",
          "SRC-002"
        ],
        "source_urls": [
          "https://www.leanderisd.org/bond_athleticsprojects/",
          "https://news.leanderisd.org/board-briefs-jan-22-2026/"
        ],
        "needs_review": true,
        "run_timestamp": "20260716T091500Z",
        "confidence": 0.75
      }
    },
    {
      "external_id": "970b96a01eacd60a",
      "source": "web-search",
      "organization": "Leander ISD",
      "organization_id": "leander-isd-tx",
      "state": "TX",
      "county": "Williamson",
      "summary": "Leander ISD's turf replacement at Ed W. Monroe Memorial Stadium (football/soccer) is actively underway as of a May 2026 status update ('the new turf is being laid out'), funded by a $1.6M Bond 2023 reallocation shared with Bible Stadium, approved by the Board Jan. 22, 2026.",
      "evidence_quote": "May 2026 The new turf is being laid out at Monroe Stadium.",
      "source_url": "https://www.leanderisd.org/bond_athleticsprojects/",
      "discovered_at": "2026-07-01T18:41:58Z",
      "location_id": "us-tx-austin-msa",
      "evidence": {
        "project_name": "Monroe Stadium - turf replacement, football/soccer field",
        "project_address": "9500 McNeil Dr, Austin, TX 78750",
        "projected_start_date": "Summer 2026 (turf removal/installation underway as of May 2026)",
        "details": "Leander ISD Board (Jan. 22, 2026) approved reallocating $1.6 million in 2023 bond project savings to fund artificial turf replacement at Ed W. Monroe Memorial Stadium (adjacent to Vandegrift HS), alongside the same reallocation for Bible Stadium. Bond Oversight Committee recommended reallocation after finding the existing turf had reached end of usable life and posed growing safety concerns; replacement scheduled for summer to avoid disrupting the athletic season. As of the district's May 2026 status update, crews had begun removing old turf with new turf installation underway. Field supports football and soccer.",
        "contact": {
          "first_name": "",
          "last_name": "",
          "title": "",
          "phone": "",
          "email": ""
        },
        "source_ids": [
          "SRC-001",
          "SRC-002"
        ],
        "source_urls": [
          "https://www.leanderisd.org/bond_athleticsprojects/",
          "https://news.leanderisd.org/board-briefs-jan-22-2026/"
        ],
        "needs_review": false,
        "run_timestamp": "20260716T091500Z",
        "confidence": 0.85
      }
    },
    {
      "external_id": "1d3cb0f9ecf08208",
      "source": "web-search",
      "organization": "Leander ISD",
      "organization_id": "leander-isd-tx",
      "state": "TX",
      "county": "Williamson",
      "summary": "Completed Leander ISD 2023 bond project: baseball/softball turf installed at five high schools (Cedar Park, Leander, Rouse, Vandegrift, Vista Ridge), awarded to Hellas Construction for $27,601,380; all five campuses confirmed complete with ribbon-cuttings Nov 2024-Mar 2025.",
      "evidence_quote": "Now all high schools in Leander ISD have fields with artificial turf.",
      "source_url": "https://www.leanderisd.org/bond_athleticsprojects/",
      "discovered_at": "2026-07-01T18:41:58Z",
      "location_id": "us-tx-austin-msa",
      "evidence": {
        "project_name": "LISD High Schools - baseball/softball turf installation",
        "project_address": "",
        "projected_start_date": "",
        "details": "Bond 2023 project: installation of artificial turf on baseball and softball fields at five high schools (Cedar Park HS, Leander HS, Rouse HS, Vandegrift HS, Vista Ridge HS); Glenn HS already had turf prior to this bond. Awarded to Hellas Construction; cost $27,601,380. Completion now confirmed with specific ribbon-cutting dates: Rouse HS (Nov 2024), Leander HS (Jan 2025), Cedar Park HS and Vista Ridge HS (Mar 2025), Vandegrift HS (Mar 2025). All five campuses complete; no further procurement action expected.",
        "contact": {
          "first_name": "",
          "last_name": "",
          "title": "",
          "phone": "",
          "email": ""
        },
        "source_ids": [
          "SRC-001"
        ],
        "source_urls": [
          "https://www.leanderisd.org/bond_athleticsprojects/"
        ],
        "needs_review": false,
        "run_timestamp": "20260716T091500Z",
        "confidence": 0.9
      }
    },
    {
      "external_id": "2b030bd4bc212e5a",
      "source": "web-search",
      "organization": "Leander ISD",
      "organization_id": "leander-isd-tx",
      "state": "TX",
      "county": "Williamson",
      "summary": "Completed Leander ISD 2023 bond project: artificial turf on the Running Brushy Middle School competition field ($1,186,500), confirmed complete as of August 2025, ready for the school year.",
      "evidence_quote": "August 2025 The artificial turf project is complete and ready for the first day of school.",
      "source_url": "https://www.leanderisd.org/bond_athleticsprojects/",
      "discovered_at": "2026-07-01T18:41:58Z",
      "location_id": "us-tx-austin-msa",
      "evidence": {
        "project_name": "Running Brushy MS - competition field turf",
        "project_address": "2303 N. Lakeline Blvd, Cedar Park, TX 78613",
        "projected_start_date": "",
        "details": "Bond 2023 project: installation of artificial turf on the competition field at Running Brushy MS, used for sub-varsity games and community rentals. Estimated project budget $1,186,500, funded by Bond 2023. Prior known lead was in-progress (Summer 2024 start); page now confirms completion as of August 2025, ready for the school year.",
        "contact": {
          "first_name": "",
          "last_name": "",
          "title": "",
          "phone": "",
          "email": ""
        },
        "source_ids": [
          "SRC-001"
        ],
        "source_urls": [
          "https://www.leanderisd.org/bond_athleticsprojects/",
          "https://www.leanderisd.org/bond_runningbrushyms/"
        ],
        "needs_review": false,
        "run_timestamp": "20260716T091500Z",
        "confidence": 0.85
      }
    },
    {
      "external_id": "01c9a4a604c64938",
      "source": "web-search",
      "organization": "Round Rock ISD",
      "organization_id": "round-rock-isd-tx",
      "state": "TX",
      "county": "Williamson",
      "summary": "Round Rock ISD's Westwood HS Athletic Improvements Phase 1 (baseball/softball field turf, track resurfacing), funded by the $932M 2024 bond, is confirmed as RFP #14629365 on the district's procurement aggregator; the solicitation closed after its Feb 19, 2026 due date with no award status yet shown.",
      "evidence_quote": "School athletic improvements - phase 1.",
      "source_url": "https://www.texasbids.net/government-agencies/williamson/round-rock-independent-school-district-purchasing-2070/",
      "discovered_at": "2026-07-01T18:41:58Z",
      "location_id": "us-tx-austin-msa",
      "evidence": {
        "project_name": "Westwood HS - baseball/softball turf, athletic improvements",
        "project_address": "12400 Mellow Meadow Drive, Austin, TX 78750",
        "projected_start_date": "",
        "details": "2024 bond package ($932M) funds installation of artificial turf on the baseball and softball fields at Westwood High School, plus running track resurfacing and other athletics facility renovations. Originally listed on the district's own procurement board (now broken, SRC-004); the district's Williamson County procurement aggregator (texasbids.net, SRC-008) confirms the formal solicitation number (RFP #14629365, due 02/19/26) and shows it as closed/past-due with no award status yet disclosed. Follow-up needed to confirm award.",
        "contact": {
          "first_name": "",
          "last_name": "",
          "title": "",
          "phone": "",
          "email": ""
        },
        "source_ids": [
          "SRC-004",
          "SRC-008"
        ],
        "source_urls": [
          "https://www.texasbids.net/government-agencies/williamson/round-rock-independent-school-district-purchasing-2070/"
        ],
        "needs_review": true,
        "run_timestamp": "20260716T091500Z",
        "confidence": 0.55
      }
    },
    {
      "external_id": "bb507db8a034c467",
      "source": "web-search",
      "organization": "Round Rock ISD",
      "organization_id": "round-rock-isd-tx",
      "state": "TX",
      "county": "Williamson",
      "summary": "Round Rock ISD's Stony Point HS Package 1 (softball/baseball field and fencing renovation, track resurfacing, new batting cages, plus roof/HVAC replacement), funded by the 2024 bond, is confirmed as RFP/bid #14492704 on the district's procurement aggregator; due 11/25/25, now past due (closed) with no award status shown.",
      "evidence_quote": "Renovations of softball and baseball field and fencing, renovations of track surfacing, addition of new pemb batting cages, replacement of roof and curbs, replacement of hvac units to include plumbing, controls and electrical connections and renovati...",
      "source_url": "https://www.texasbids.net/government-agencies/williamson/round-rock-independent-school-district-purchasing-2070/",
      "discovered_at": "2026-07-01T18:41:58Z",
      "location_id": "us-tx-austin-msa",
      "evidence": {
        "project_name": "Stony Point HS - softball/baseball field renovation Package 1",
        "project_address": "1801 Tiger Trail, Round Rock, TX 78664",
        "projected_start_date": "",
        "details": "Active bid 'Stony Point HS - Package 1' for renovation of softball and baseball fields and fencing, track surfacing renovation, new PEMB batting cage addition. Originally listed on the district's own e-bid page (now broken, SRC-004); the district's Williamson County procurement aggregator (texasbids.net, SRC-008) confirms the formal bid number (#14492704, due 11/25/25), shows it closed/past-due with no award disclosed, and adds roof/curb and HVAC replacement scope not previously recorded. Turf-material specifics for the softball/baseball fields still require validation.",
        "contact": {
          "first_name": "",
          "last_name": "",
          "title": "",
          "phone": "",
          "email": ""
        },
        "source_ids": [
          "SRC-004",
          "SRC-008"
        ],
        "source_urls": [
          "https://www.texasbids.net/government-agencies/williamson/round-rock-independent-school-district-purchasing-2070/"
        ],
        "needs_review": true,
        "run_timestamp": "20260716T091500Z",
        "confidence": 0.6
      }
    }
  ]
}
